{
    "annotations": {
        "list": [
            {
                "builtIn": 1,
                "datasource": {
                    "type": "datasource",
                    "uid": "grafana"
                },
                "enable": true,
                "hide": true,
                "iconColor": "rgba(0, 211, 255, 1)",
                "name": "Annotations & Alerts",
                "target": {
                    "limit": 100,
                    "matchAny": false,
                    "tags": [],
                    "type": "dashboard"
                },
                "type": "dashboard"
            }
        ]
    },
    "description": "Dashboard with details of the containers and host metrics for Raspberry Pi, based from work of Oijkn.",
    "editable": true,
    "fiscalYearStartMonth": 0,
    "gnetId": 19275,
    "graphTooltip": 1,
    "links": [],
    "liveNow": false,
    "panels": [
        {
            "datasource": {
                "type": "prometheus",
                "uid": "P1809F7CD0C75ACF3"
            },
            "description": "Hardware temperature",
            "fieldConfig": {
                "defaults": {
                    "color": {
                        "mode": "thresholds"
                    },
                    "decimals": 2,
                    "displayName": "${__field.labels[\"pi_name\"]}",
                    "mappings": [
                        {
                            "options": {
                                "match": "null",
                                "result": {
                                    "text": "N/A"
                                }
                            },
                            "type": "special"
                        }
                    ],
                    "max": 75,
                    "min": 0,
                    "thresholds": {
                        "mode": "absolute",
                        "steps": [
                            {
                                "color": "rgba(50, 172, 45, 0.97)",
                                "value": null
                            },
                            {
                                "color": "#EAB839",
                                "value": 60
                            },
                            {
                                "color": "rgba(237, 129, 40, 0.89)",
                                "value": 65
                            },
                            {
                                "color": "rgba(245, 54, 54, 0.9)",
                                "value": 70
                            }
                        ]
                    },
                    "unit": "celsius",
                    "unitScale": true
                },
                "overrides": []
            },
            "gridPos": {
                "h": 6,
                "w": 12,
                "x": 0,
                "y": 0
            },
            "id": 44,
            "links": [],
            "maxDataPoints": 100,
            "options": {
                "minVizHeight": 200,
                "minVizWidth": 200,
                "orientation": "vertical",
                "reduceOptions": {
                    "calcs": [
                        "lastNotNull"
                    ],
                    "fields": "",
                    "values": false
                },
                "showThresholdLabels": false,
                "showThresholdMarkers": true,
                "sizing": "auto",
                "text": {}
            },
            "pluginVersion": "10.4.0-157238",
            "targets": [
                {
                    "datasource": {
                        "type": "prometheus",
                        "uid": "P1809F7CD0C75ACF3"
                    },
                    "editorMode": "code",
                    "exemplar": true,
                    "expr": "node_thermal_zone_temp{type=\"cpu-thermal\"}",
                    "format": "time_series",
                    "hide": false,
                    "interval": "",
                    "intervalFactor": 2,
                    "legendFormat": "",
                    "range": true,
                    "refId": "A",
                    "step": 1800
                }
            ],
            "title": "Temp",
            "type": "gauge"
        },
        {
            "datasource": {
                "type": "prometheus",
                "uid": "P1809F7CD0C75ACF3"
            },
            "description": "Running containers",
            "fieldConfig": {
                "defaults": {
                    "color": {
                        "mode": "thresholds"
                    },
                    "mappings": [],
                    "thresholds": {
                        "mode": "absolute",
                        "steps": [
                            {
                                "color": "green",
                                "value": null
                            },
                            {
                                "color": "red",
                                "value": 10
                            }
                        ]
                    },
                    "unitScale": true
                },
                "overrides": []
            },
            "gridPos": {
                "h": 3,
                "w": 3,
                "x": 12,
                "y": 0
            },
            "id": 90,
            "options": {
                "colorMode": "value",
                "graphMode": "none",
                "justifyMode": "auto",
                "orientation": "auto",
                "reduceOptions": {
                    "calcs": [
                        "lastNotNull"
                    ],
                    "fields": "",
                    "values": false
                },
                "showPercentChange": false,
                "textMode": "auto",
                "wideLayout": true
            },
            "pluginVersion": "10.4.0-157238",
            "targets": [
                {
                    "datasource": {
                        "type": "prometheus",
                        "uid": "P1809F7CD0C75ACF3"
                    },
                    "editorMode": "code",
                    "expr": "count(container_last_seen{image!=\"\"})",
                    "instant": false,
                    "legendFormat": "__auto",
                    "range": true,
                    "refId": "A"
                }
            ],
            "title": "Running containers",
            "type": "stat"
        },
        {
            "datasource": {
                "type": "prometheus",
                "uid": "P1809F7CD0C75ACF3"
            },
            "description": "Total Memory Usage",
            "fieldConfig": {
                "defaults": {
                    "color": {
                        "mode": "thresholds"
                    },
                    "mappings": [],
                    "thresholds": {
                        "mode": "absolute",
                        "steps": [
                            {
                                "color": "green",
                                "value": null
                            },
                            {
                                "color": "#EAB839",
                                "value": 400
                            },
                            {
                                "color": "#EF843C",
                                "value": 500
                            },
                            {
                                "color": "#E24D42",
                                "value": 600
                            }
                        ]
                    },
                    "unit": "Mib",
                    "unitScale": true
                },
                "overrides": []
            },
            "gridPos": {
                "h": 3,
                "w": 3,
                "x": 15,
                "y": 0
            },
            "id": 89,
            "options": {
                "colorMode": "value",
                "graphMode": "none",
                "justifyMode": "center",
                "orientation": "auto",
                "reduceOptions": {
                    "calcs": [
                        "lastNotNull"
                    ],
                    "fields": "",
                    "values": false
                },
                "showPercentChange": false,
                "textMode": "auto",
                "wideLayout": true
            },
            "pluginVersion": "10.4.0-157238",
            "targets": [
                {
                    "datasource": {
                        "type": "prometheus",
                        "uid": "P1809F7CD0C75ACF3"
                    },
                    "editorMode": "code",
                    "expr": "sum(container_memory_usage_bytes{image!=\"\"})/1024/1024",
                    "instant": false,
                    "legendFormat": "__auto",
                    "range": true,
                    "refId": "A"
                }
            ],
            "title": "Total Memory Usage",
            "type": "stat"
        },
        {
            "datasource": {
                "type": "prometheus",
                "uid": "P1809F7CD0C75ACF3"
            },
            "description": "Total Memory Usage",
            "fieldConfig": {
                "defaults": {
                    "color": {
                        "mode": "thresholds"
                    },
                    "mappings": [],
                    "thresholds": {
                        "mode": "absolute",
                        "steps": [
                            {
                                "color": "text",
                                "value": null
                            }
                        ]
                    },
                    "unit": "Mib",
                    "unitScale": true
                },
                "overrides": []
            },
            "gridPos": {
                "h": 3,
                "w": 3,
                "x": 18,
                "y": 0
            },
            "id": 91,
            "options": {
                "colorMode": "value",
                "graphMode": "none",
                "justifyMode": "center",
                "orientation": "auto",
                "reduceOptions": {
                    "calcs": [
                        "lastNotNull"
                    ],
                    "fields": "",
                    "values": false
                },
                "showPercentChange": false,
                "textMode": "auto",
                "wideLayout": true
            },
            "pluginVersion": "10.4.0-157238",
            "targets": [
                {
                    "datasource": {
                        "type": "prometheus",
                        "uid": "P1809F7CD0C75ACF3"
                    },
                    "editorMode": "code",
                    "expr": "sum(node_memory_MemTotal_bytes)/1024/1024",
                    "instant": false,
                    "legendFormat": "__auto",
                    "range": true,
                    "refId": "A"
                }
            ],
            "title": "Total Memory Usage",
            "type": "stat"
        },
        {
            "datasource": {
                "type": "prometheus",
                "uid": "P1809F7CD0C75ACF3"
            },
            "description": "Total number of CPU cores",
            "fieldConfig": {
                "defaults": {
                    "color": {
                        "mode": "thresholds"
                    },
                    "mappings": [
                        {
                            "options": {
                                "match": "null",
                                "result": {
                                    "text": "N/A"
                                }
                            },
                            "type": "special"
                        }
                    ],
                    "thresholds": {
                        "mode": "absolute",
                        "steps": [
                            {
                                "color": "green",
                                "value": null
                            },
                            {
                                "color": "red",
                                "value": 80
                            }
                        ]
                    },
                    "unit": "short",
                    "unitScale": true
                },
                "overrides": []
            },
            "gridPos": {
                "h": 3,
                "w": 3,
                "x": 21,
                "y": 0
            },
            "id": 68,
            "links": [],
            "maxDataPoints": 100,
            "options": {
                "colorMode": "none",
                "graphMode": "none",
                "justifyMode": "auto",
                "orientation": "horizontal",
                "reduceOptions": {
                    "calcs": [
                        "lastNotNull"
                    ],
                    "fields": "",
                    "values": false
                },
                "showPercentChange": false,
                "textMode": "auto",
                "wideLayout": true
            },
            "pluginVersion": "10.4.0-157238",
            "targets": [
                {
                    "datasource": {
                        "type": "prometheus",
                        "uid": "P1809F7CD0C75ACF3"
                    },
                    "editorMode": "code",
                    "expr": "count(count(node_cpu_seconds_total) by (cpu))",
                    "legendFormat": "__auto",
                    "range": true,
                    "refId": "A"
                }
            ],
            "title": "CPU Cores",
            "type": "stat"
        },
        {
            "datasource": {
                "type": "prometheus",
                "uid": "P1809F7CD0C75ACF3"
            },
            "fieldConfig": {
                "defaults": {
                    "color": {
                        "mode": "palette-classic"
                    },
                    "custom": {
                        "axisBorderShow": false,
                        "axisCenteredZero": false,
                        "axisColorMode": "text",
                        "axisLabel": "",
                        "axisPlacement": "auto",
                        "barAlignment": 0,
                        "drawStyle": "line",
                        "fillOpacity": 10,
                        "gradientMode": "none",
                        "hideFrom": {
                            "legend": false,
                            "tooltip": false,
                            "viz": false
                        },
                        "insertNulls": false,
                        "lineInterpolation": "smooth",
                        "lineWidth": 2,
                        "pointSize": 5,
                        "scaleDistribution": {
                            "type": "linear"
                        },
                        "showPoints": "never",
                        "spanNulls": false,
                        "stacking": {
                            "group": "A",
                            "mode": "none"
                        },
                        "thresholdsStyle": {
                            "mode": "off"
                        }
                    },
                    "displayName": "${__field.labels[\"pi_name\"]}",
                    "mappings": [],
                    "thresholds": {
                        "mode": "absolute",
                        "steps": [
                            {
                                "color": "green",
                                "value": null
                            },
                            {
                                "color": "red",
                                "value": 80
                            }
                        ]
                    },
                    "unit": "short",
                    "unitScale": true
                },
                "overrides": []
            },
            "gridPos": {
                "h": 9,
                "w": 12,
                "x": 12,
                "y": 3
            },
            "id": 84,
            "options": {
                "legend": {
                    "calcs": [
                        "min",
                        "max"
                    ],
                    "displayMode": "table",
                    "placement": "bottom",
                    "showLegend": false
                },
                "tooltip": {
                    "mode": "multi",
                    "sort": "desc"
                }
            },
            "pluginVersion": "9.3.2",
            "targets": [
                {
                    "datasource": {
                        "type": "prometheus",
                        "uid": "P1809F7CD0C75ACF3"
                    },
                    "editorMode": "code",
                    "expr": "node_thermal_zone_temp\n",
                    "hide": false,
                    "interval": "",
                    "legendFormat": "{{name}}",
                    "range": true,
                    "refId": "A"
                }
            ],
            "title": "CPU Temperature",
            "type": "timeseries"
        },
        {
            "datasource": {
                "type": "prometheus",
                "uid": "P1809F7CD0C75ACF3"
            },
            "description": "Used Root FS",
            "fieldConfig": {
                "defaults": {
                    "color": {
                        "mode": "thresholds"
                    },
                    "displayName": "${__field.labels[\"pi_name\"]}",
                    "mappings": [
                        {
                            "options": {
                                "match": "null",
                                "result": {
                                    "text": "N/A"
                                }
                            },
                            "type": "special"
                        }
                    ],
                    "max": 100,
                    "min": 0,
                    "thresholds": {
                        "mode": "absolute",
                        "steps": [
                            {
                                "color": "rgba(50, 172, 45, 0.97)",
                                "value": null
                            },
                            {
                                "color": "rgba(237, 129, 40, 0.89)",
                                "value": 80
                            },
                            {
                                "color": "rgba(245, 54, 54, 0.9)",
                                "value": 90
                            }
                        ]
                    },
                    "unit": "percent",
                    "unitScale": true
                },
                "overrides": []
            },
            "gridPos": {
                "h": 6,
                "w": 12,
                "x": 0,
                "y": 6
            },
            "id": 26,
            "links": [],
            "maxDataPoints": 100,
            "options": {
                "minVizHeight": 200,
                "minVizWidth": 200,
                "orientation": "vertical",
                "reduceOptions": {
                    "calcs": [
                        "lastNotNull"
                    ],
                    "fields": "",
                    "values": false
                },
                "showThresholdLabels": false,
                "showThresholdMarkers": true,
                "sizing": "auto",
                "text": {}
            },
            "pluginVersion": "10.4.0-157238",
            "targets": [
                {
                    "datasource": {
                        "type": "prometheus",
                        "uid": "P1809F7CD0C75ACF3"
                    },
                    "editorMode": "code",
                    "exemplar": true,
                    "expr": "100 - ((node_filesystem_avail_bytes{mountpoint=\"/\",fstype!=\"rootfs\"} * 100) / node_filesystem_size_bytes{mountpoint=\"/\",fstype!=\"rootfs\"})",
                    "format": "time_series",
                    "hide": false,
                    "interval": "",
                    "intervalFactor": 2,
                    "legendFormat": "/",
                    "range": true,
                    "refId": "A",
                    "step": 1800
                }
            ],
            "title": "Root FS Used",
            "type": "gauge"
        },
        {
            "datasource": {
                "type": "prometheus",
                "uid": "P1809F7CD0C75ACF3"
            },
            "description": "Non available RAM memory",
            "fieldConfig": {
                "defaults": {
                    "color": {
                        "mode": "thresholds"
                    },
                    "decimals": 0,
                    "displayName": "${__field.labels[\"pi_name\"]}",
                    "mappings": [],
                    "max": 100,
                    "min": 0,
                    "thresholds": {
                        "mode": "absolute",
                        "steps": [
                            {
                                "color": "rgba(50, 172, 45, 0.97)",
                                "value": null
                            },
                            {
                                "color": "rgba(237, 129, 40, 0.89)",
                                "value": 80
                            },
                            {
                                "color": "rgba(245, 54, 54, 0.9)",
                                "value": 90
                            }
                        ]
                    },
                    "unit": "percent",
                    "unitScale": true
                },
                "overrides": []
            },
            "gridPos": {
                "h": 6,
                "w": 12,
                "x": 0,
                "y": 12
            },
            "hideTimeOverride": false,
            "id": 54,
            "links": [],
            "options": {
                "minVizHeight": 200,
                "minVizWidth": 200,
                "orientation": "vertical",
                "reduceOptions": {
                    "calcs": [
                        "lastNotNull"
                    ],
                    "fields": "",
                    "values": false
                },
                "showThresholdLabels": false,
                "showThresholdMarkers": true,
                "sizing": "auto",
                "text": {}
            },
            "pluginVersion": "10.4.0-157238",
            "targets": [
                {
                    "datasource": {
                        "type": "prometheus",
                        "uid": "P1809F7CD0C75ACF3"
                    },
                    "editorMode": "code",
                    "exemplar": true,
                    "expr": "((container_memory_MemTotal_bytes - container_memory_MemFree_bytes) / (container_memory_MemTotal_bytes )) * 100",
                    "format": "time_series",
                    "hide": true,
                    "interval": "",
                    "intervalFactor": 1,
                    "legendFormat": "",
                    "range": true,
                    "refId": "A",
                    "step": 240
                },
                {
                    "datasource": {
                        "type": "prometheus",
                        "uid": "P1809F7CD0C75ACF3"
                    },
                    "editorMode": "code",
                    "exemplar": true,
                    "expr": "100 - ((node_memory_MemAvailable_bytes * 100) / node_memory_MemTotal_bytes)",
                    "format": "time_series",
                    "hide": false,
                    "interval": "",
                    "intervalFactor": 1,
                    "legendFormat": "",
                    "range": true,
                    "refId": "B",
                    "step": 240
                }
            ],
            "title": "RAM Used",
            "type": "gauge"
        },
        {
            "datasource": {
                "type": "prometheus",
                "uid": "P1809F7CD0C75ACF3"
            },
            "description": "System uptime",
            "fieldConfig": {
                "defaults": {
                    "color": {
                        "mode": "thresholds"
                    },
                    "decimals": 1,
                    "mappings": [
                        {
                            "options": {
                                "match": "null",
                                "result": {
                                    "text": "N/A"
                                }
                            },
                            "type": "special"
                        }
                    ],
                    "thresholds": {
                        "mode": "absolute",
                        "steps": [
                            {
                                "color": "green",
                                "value": null
                            },
                            {
                                "color": "red",
                                "value": 80
                            }
                        ]
                    },
                    "unit": "s",
                    "unitScale": true
                },
                "overrides": []
            },
            "gridPos": {
                "h": 15,
                "w": 3,
                "x": 12,
                "y": 12
            },
            "hideTimeOverride": true,
            "id": 70,
            "links": [],
            "maxDataPoints": 100,
            "options": {
                "colorMode": "none",
                "graphMode": "none",
                "justifyMode": "auto",
                "orientation": "horizontal",
                "reduceOptions": {
                    "calcs": [
                        "lastNotNull"
                    ],
                    "fields": "",
                    "values": false
                },
                "showPercentChange": false,
                "textMode": "auto",
                "wideLayout": true
            },
            "pluginVersion": "10.4.0-157238",
            "targets": [
                {
                    "datasource": {
                        "type": "prometheus",
                        "uid": "P1809F7CD0C75ACF3"
                    },
                    "editorMode": "code",
                    "expr": "node_time_seconds - node_boot_time_seconds",
                    "legendFormat": "__auto",
                    "range": true,
                    "refId": "A"
                }
            ],
            "title": "Uptime",
            "type": "stat"
        },
        {
            "datasource": {
                "type": "prometheus",
                "uid": "P1809F7CD0C75ACF3"
            },
            "description": "Total RAM",
            "fieldConfig": {
                "defaults": {
                    "color": {
                        "mode": "thresholds"
                    },
                    "decimals": 0,
                    "mappings": [
                        {
                            "options": {
                                "match": "null",
                                "result": {
                                    "text": "N/A"
                                }
                            },
                            "type": "special"
                        }
                    ],
                    "thresholds": {
                        "mode": "absolute",
                        "steps": [
                            {
                                "color": "green",
                                "value": null
                            },
                            {
                                "color": "red",
                                "value": 80
                            }
                        ]
                    },
                    "unit": "bytes",
                    "unitScale": true
                },
                "overrides": []
            },
            "gridPos": {
                "h": 15,
                "w": 3,
                "x": 15,
                "y": 12
            },
            "id": 74,
            "links": [],
            "maxDataPoints": 100,
            "options": {
                "colorMode": "none",
                "graphMode": "none",
                "justifyMode": "auto",
                "orientation": "horizontal",
                "reduceOptions": {
                    "calcs": [
                        "last"
                    ],
                    "fields": "",
                    "values": false
                },
                "showPercentChange": false,
                "textMode": "auto",
                "wideLayout": true
            },
            "pluginVersion": "10.4.0-157238",
            "targets": [
                {
                    "datasource": {
                        "type": "prometheus",
                        "uid": "P1809F7CD0C75ACF3"
                    },
                    "editorMode": "code",
                    "expr": "node_memory_MemTotal_bytes",
                    "legendFormat": "__auto",
                    "range": true,
                    "refId": "A"
                }
            ],
            "title": "RAM Total",
            "type": "stat"
        },
        {
            "datasource": {
                "type": "prometheus",
                "uid": "P1809F7CD0C75ACF3"
            },
            "description": "Total RootFS",
            "fieldConfig": {
                "defaults": {
                    "color": {
                        "mode": "thresholds"
                    },
                    "decimals": 0,
                    "mappings": [
                        {
                            "options": {
                                "match": "null",
                                "result": {
                                    "text": "N/A"
                                }
                            },
                            "type": "special"
                        }
                    ],
                    "thresholds": {
                        "mode": "absolute",
                        "steps": [
                            {
                                "color": "rgba(50, 172, 45, 0.97)",
                                "value": null
                            },
                            {
                                "color": "rgba(237, 129, 40, 0.89)",
                                "value": 70
                            },
                            {
                                "color": "rgba(245, 54, 54, 0.9)",
                                "value": 90
                            }
                        ]
                    },
                    "unit": "bytes",
                    "unitScale": true
                },
                "overrides": []
            },
            "gridPos": {
                "h": 12,
                "w": 3,
                "x": 18,
                "y": 12
            },
            "id": 72,
            "links": [],
            "maxDataPoints": 100,
            "options": {
                "colorMode": "none",
                "graphMode": "none",
                "justifyMode": "auto",
                "orientation": "horizontal",
                "reduceOptions": {
                    "calcs": [
                        "lastNotNull"
                    ],
                    "fields": "",
                    "values": false
                },
                "showPercentChange": false,
                "textMode": "auto",
                "wideLayout": true
            },
            "pluginVersion": "10.4.0-157238",
            "targets": [
                {
                    "datasource": {
                        "type": "prometheus",
                        "uid": "P1809F7CD0C75ACF3"
                    },
                    "editorMode": "code",
                    "expr": "node_filesystem_size_bytes{mountpoint=\"/\",fstype!=\"rootfs\"}",
                    "legendFormat": "__auto",
                    "range": true,
                    "refId": "A"
                }
            ],
            "title": "RootFS Total",
            "type": "stat"
        },
        {
            "datasource": {
                "type": "prometheus",
                "uid": "P1809F7CD0C75ACF3"
            },
            "description": "Busy state of all CPU cores together",
            "fieldConfig": {
                "defaults": {
                    "color": {
                        "mode": "thresholds"
                    },
                    "mappings": [
                        {
                            "options": {
                                "match": "null",
                                "result": {
                                    "text": "N/A"
                                }
                            },
                            "type": "special"
                        }
                    ],
                    "max": 100,
                    "min": 0,
                    "thresholds": {
                        "mode": "absolute",
                        "steps": [
                            {
                                "color": "rgba(50, 172, 45, 0.97)",
                                "value": null
                            },
                            {
                                "color": "rgba(237, 129, 40, 0.89)",
                                "value": 85
                            },
                            {
                                "color": "rgba(245, 54, 54, 0.9)",
                                "value": 95
                            }
                        ]
                    },
                    "unit": "percent",
                    "unitScale": true
                },
                "overrides": []
            },
            "gridPos": {
                "h": 6,
                "w": 3,
                "x": 0,
                "y": 18
            },
            "id": 52,
            "links": [],
            "options": {
                "minVizHeight": 200,
                "minVizWidth": 200,
                "orientation": "horizontal",
                "reduceOptions": {
                    "calcs": [
                        "lastNotNull"
                    ],
                    "fields": "",
                    "values": false
                },
                "showThresholdLabels": false,
                "showThresholdMarkers": true,
                "sizing": "auto",
                "text": {}
            },
            "pluginVersion": "10.4.0-157238",
            "targets": [
                {
                    "datasource": {
                        "type": "prometheus",
                        "uid": "P1809F7CD0C75ACF3"
                    },
                    "editorMode": "code",
                    "exemplar": true,
                    "expr": "(sum by(instance) (irate(node_cpu_seconds_total{mode!=\"idle\"}[$__rate_interval])) / on(instance) group_left sum by (instance)((irate(node_cpu_seconds_total[$__rate_interval])))) * 100",
                    "hide": false,
                    "interval": "",
                    "intervalFactor": 1,
                    "legendFormat": "",
                    "range": true,
                    "refId": "A",
                    "step": 240
                }
            ],
            "title": "CPU Busy",
            "type": "gauge"
        },
        {
            "datasource": {
                "type": "prometheus",
                "uid": "P1809F7CD0C75ACF3"
            },
            "description": "Busy state of all CPU cores together (5 min average)",
            "fieldConfig": {
                "defaults": {
                    "color": {
                        "mode": "thresholds"
                    },
                    "mappings": [
                        {
                            "options": {
                                "match": "null",
                                "result": {
                                    "text": "N/A"
                                }
                            },
                            "type": "special"
                        }
                    ],
                    "max": 100,
                    "min": 0,
                    "thresholds": {
                        "mode": "absolute",
                        "steps": [
                            {
                                "color": "rgba(50, 172, 45, 0.97)",
                                "value": null
                            },
                            {
                                "color": "rgba(237, 129, 40, 0.89)",
                                "value": 85
                            },
                            {
                                "color": "rgba(245, 54, 54, 0.9)",
                                "value": 95
                            }
                        ]
                    },
                    "unit": "percent",
                    "unitScale": true
                },
                "overrides": []
            },
            "gridPos": {
                "h": 6,
                "w": 3,
                "x": 3,
                "y": 18
            },
            "id": 58,
            "links": [],
            "options": {
                "minVizHeight": 200,
                "minVizWidth": 200,
                "orientation": "horizontal",
                "reduceOptions": {
                    "calcs": [
                        "lastNotNull"
                    ],
                    "fields": "",
                    "values": false
                },
                "showThresholdLabels": false,
                "showThresholdMarkers": true,
                "sizing": "auto",
                "text": {}
            },
            "pluginVersion": "10.4.0-157238",
            "targets": [
                {
                    "datasource": {
                        "type": "prometheus",
                        "uid": "P1809F7CD0C75ACF3"
                    },
                    "editorMode": "code",
                    "exemplar": true,
                    "expr": "avg(node_load5) /  count(count(node_cpu_seconds_total) by (cpu)) * 100",
                    "format": "time_series",
                    "hide": false,
                    "interval": "",
                    "intervalFactor": 1,
                    "legendFormat": "",
                    "range": true,
                    "refId": "A",
                    "step": 240
                }
            ],
            "title": "Sys Load (5m avg)",
            "type": "gauge"
        },
        {
            "datasource": {
                "type": "prometheus",
                "uid": "P1809F7CD0C75ACF3"
            },
            "fieldConfig": {
                "defaults": {
                    "color": {
                        "mode": "palette-classic"
                    },
                    "custom": {
                        "axisBorderShow": false,
                        "axisCenteredZero": false,
                        "axisColorMode": "text",
                        "axisLabel": "",
                        "axisPlacement": "auto",
                        "barAlignment": 0,
                        "drawStyle": "line",
                        "fillOpacity": 10,
                        "gradientMode": "none",
                        "hideFrom": {
                            "legend": false,
                            "tooltip": false,
                            "viz": false
                        },
                        "insertNulls": false,
                        "lineInterpolation": "smooth",
                        "lineWidth": 2,
                        "pointSize": 5,
                        "scaleDistribution": {
                            "type": "linear"
                        },
                        "showPoints": "never",
                        "spanNulls": false,
                        "stacking": {
                            "group": "A",
                            "mode": "none"
                        },
                        "thresholdsStyle": {
                            "mode": "off"
                        }
                    },
                    "mappings": [],
                    "thresholds": {
                        "mode": "absolute",
                        "steps": [
                            {
                                "color": "green",
                                "value": null
                            },
                            {
                                "color": "red",
                                "value": 80
                            }
                        ]
                    },
                    "unit": "Bps",
                    "unitScale": true
                },
                "overrides": []
            },
            "gridPos": {
                "h": 8,
                "w": 12,
                "x": 0,
                "y": 24
            },
            "id": 82,
            "options": {
                "legend": {
                    "calcs": [
                        "mean",
                        "max"
                    ],
                    "displayMode": "table",
                    "placement": "right",
                    "showLegend": true
                },
                "tooltip": {
                    "mode": "multi",
                    "sort": "desc"
                }
            },
            "pluginVersion": "9.3.2",
            "targets": [
                {
                    "datasource": {
                        "type": "prometheus",
                        "uid": "P1809F7CD0C75ACF3"
                    },
                    "editorMode": "code",
                    "expr": "sum(rate(container_network_receive_bytes_total{name=~\".+\"}[$__rate_interval])) by (name)",
                    "hide": false,
                    "interval": "",
                    "legendFormat": "{{name}}",
                    "range": true,
                    "refId": "A"
                }
            ],
            "title": "Received Network Traffic",
            "type": "timeseries"
        },
        {
            "datasource": {
                "type": "prometheus",
                "uid": "P1809F7CD0C75ACF3"
            },
            "fieldConfig": {
                "defaults": {
                    "color": {
                        "mode": "palette-classic"
                    },
                    "custom": {
                        "axisBorderShow": false,
                        "axisCenteredZero": false,
                        "axisColorMode": "text",
                        "axisLabel": "",
                        "axisPlacement": "auto",
                        "barAlignment": 0,
                        "drawStyle": "line",
                        "fillOpacity": 10,
                        "gradientMode": "none",
                        "hideFrom": {
                            "legend": false,
                            "tooltip": false,
                            "viz": false
                        },
                        "insertNulls": false,
                        "lineInterpolation": "linear",
                        "lineWidth": 2,
                        "pointSize": 5,
                        "scaleDistribution": {
                            "type": "linear"
                        },
                        "showPoints": "never",
                        "spanNulls": true,
                        "stacking": {
                            "group": "A",
                            "mode": "none"
                        },
                        "thresholdsStyle": {
                            "mode": "off"
                        }
                    },
                    "decimals": 1,
                    "mappings": [],
                    "thresholds": {
                        "mode": "absolute",
                        "steps": [
                            {
                                "color": "green",
                                "value": null
                            },
                            {
                                "color": "red",
                                "value": 80
                            }
                        ]
                    },
                    "unit": "bytes",
                    "unitScale": true
                },
                "overrides": []
            },
            "gridPos": {
                "h": 8,
                "w": 12,
                "x": 12,
                "y": 27
            },
            "id": 38,
            "links": [],
            "options": {
                "legend": {
                    "calcs": [],
                    "displayMode": "table",
                    "placement": "right",
                    "showLegend": true
                },
                "tooltip": {
                    "mode": "multi",
                    "sort": "desc"
                }
            },
            "pluginVersion": "8.1.5",
            "targets": [
                {
                    "datasource": {
                        "type": "prometheus",
                        "uid": "P1809F7CD0C75ACF3"
                    },
                    "editorMode": "code",
                    "expr": "container_memory_usage_bytes{name!=\"\"}",
                    "format": "time_series",
                    "hide": false,
                    "interval": "",
                    "intervalFactor": 2,
                    "legendFormat": "{{name}}",
                    "range": true,
                    "refId": "A",
                    "target": ""
                },
                {
                    "datasource": {
                        "type": "prometheus",
                        "uid": "P1809F7CD0C75ACF3"
                    },
                    "editorMode": "code",
                    "expr": "container_spec_memory_limit_bytes{name!=\"\"}",
                    "format": "time_series",
                    "hide": true,
                    "interval": "",
                    "intervalFactor": 2,
                    "legendFormat": "Limit {{name}}",
                    "range": true,
                    "refId": "B"
                }
            ],
            "title": "Used Memory",
            "type": "timeseries"
        },
        {
            "datasource": {
                "type": "prometheus",
                "uid": "P1809F7CD0C75ACF3"
            },
            "fieldConfig": {
                "defaults": {
                    "color": {
                        "mode": "palette-classic"
                    },
                    "custom": {
                        "axisBorderShow": false,
                        "axisCenteredZero": false,
                        "axisColorMode": "text",
                        "axisLabel": "",
                        "axisPlacement": "auto",
                        "barAlignment": 0,
                        "drawStyle": "line",
                        "fillOpacity": 10,
                        "gradientMode": "none",
                        "hideFrom": {
                            "legend": false,
                            "tooltip": false,
                            "viz": false
                        },
                        "insertNulls": false,
                        "lineInterpolation": "smooth",
                        "lineWidth": 2,
                        "pointSize": 5,
                        "scaleDistribution": {
                            "type": "linear"
                        },
                        "showPoints": "never",
                        "spanNulls": false,
                        "stacking": {
                            "group": "A",
                            "mode": "none"
                        },
                        "thresholdsStyle": {
                            "mode": "off"
                        }
                    },
                    "mappings": [],
                    "thresholds": {
                        "mode": "absolute",
                        "steps": [
                            {
                                "color": "green",
                                "value": null
                            },
                            {
                                "color": "red",
                                "value": 80
                            }
                        ]
                    },
                    "unit": "Bps",
                    "unitScale": true
                },
                "overrides": []
            },
            "gridPos": {
                "h": 8,
                "w": 12,
                "x": 12,
                "y": 35
            },
            "id": 86,
            "options": {
                "legend": {
                    "calcs": [
                        "mean",
                        "max"
                    ],
                    "displayMode": "table",
                    "placement": "right",
                    "showLegend": true
                },
                "tooltip": {
                    "mode": "multi",
                    "sort": "desc"
                }
            },
            "pluginVersion": "9.3.2",
            "targets": [
                {
                    "datasource": {
                        "type": "prometheus",
                        "uid": "P1809F7CD0C75ACF3"
                    },
                    "editorMode": "code",
                    "expr": "sum(rate(container_network_transmit_bytes_total{name=~\".+\"}[$__rate_interval])) by (name)",
                    "interval": "",
                    "legendFormat": "{{name}}",
                    "range": true,
                    "refId": "A"
                }
            ],
            "title": "Sent Network Traffic",
            "type": "timeseries"
        },
        {
            "datasource": {
                "type": "prometheus",
                "uid": "P1809F7CD0C75ACF3"
            },
            "fieldConfig": {
                "defaults": {
                    "custom": {
                        "align": "auto",
                        "cellOptions": {
                            "type": "auto"
                        },
                        "filterable": false,
                        "inspect": false
                    },
                    "mappings": [],
                    "thresholds": {
                        "mode": "absolute",
                        "steps": [
                            {
                                "color": "green"
                            },
                            {
                                "color": "red",
                                "value": 80
                            }
                        ]
                    },
                    "unitScale": true
                },
                "overrides": [
                    {
                        "matcher": {
                            "id": "byName",
                            "options": "id"
                        },
                        "properties": [
                            {
                                "id": "custom.width",
                                "value": 260
                            }
                        ]
                    },
                    {
                        "matcher": {
                            "id": "byName",
                            "options": "Running"
                        },
                        "properties": [
                            {
                                "id": "unit",
                                "value": "d"
                            },
                            {
                                "id": "decimals",
                                "value": 1
                            },
                            {
                                "id": "custom.cellOptions",
                                "value": {
                                    "type": "color-text"
                                }
                            },
                            {
                                "id": "color",
                                "value": {
                                    "fixedColor": "dark-green",
                                    "mode": "fixed"
                                }
                            }
                        ]
                    }
                ]
            },
            "gridPos": {
                "h": 10,
                "w": 24,
                "x": 0,
                "y": 43
            },
            "id": 88,
            "options": {
                "cellHeight": "sm",
                "footer": {
                    "countRows": false,
                    "fields": "",
                    "reducer": [
                        "sum"
                    ],
                    "show": false
                },
                "showHeader": true,
                "sortBy": []
            },
            "pluginVersion": "10.4.0-157238",
            "targets": [
                {
                    "datasource": {
                        "type": "prometheus",
                        "uid": "P1809F7CD0C75ACF3"
                    },
                    "editorMode": "code",
                    "expr": "(time() - container_start_time_seconds{name=~\".+\"})/86400",
                    "format": "table",
                    "instant": true,
                    "interval": "",
                    "legendFormat": "{{name}}",
                    "refId": "A"
                }
            ],
            "title": "Containers Info",
            "transformations": [
                {
                    "id": "filterFieldsByName",
                    "options": {
                        "include": {
                            "names": [
                                "container_label_com_docker_compose_project",
                                "container_label_com_docker_compose_project_working_dir",
                                "image",
                                "instance",
                                "name",
                                "Value",
                                "container_label_com_docker_compose_service"
                            ]
                        }
                    }
                },
                {
                    "id": "organize",
                    "options": {
                        "excludeByName": {},
                        "indexByName": {},
                        "renameByName": {
                            "Value": "Running",
                            "container_label_com_docker_compose_project": "Label",
                            "container_label_com_docker_compose_project_working_dir": "Working dir",
                            "container_label_com_docker_compose_service": "Service",
                            "image": "Registry Image",
                            "instance": "Instance",
                            "name": "Name"
                        }
                    }
                }
            ],
            "type": "table"
        }
    ],
    "refresh": "10s",
    "schemaVersion": 39,
    "tags": [
        "prometheus",
        "cAdvisor",
        "node-exporter"
    ],
    "templating": {
        "list": []
    },
    "time": {
        "from": "now-5m",
        "to": "now"
    },
    "timepicker": {
        "refresh_intervals": [
            "5s",
            "10s",
            "30s",
            "1m",
            "5m",
            "15m",
            "30m",
            "1h",
            "2h",
            "1d"
        ],
        "time_options": [
            "5m",
            "15m",
            "1h",
            "6h",
            "12h",
            "24h",
            "2d",
            "7d",
            "30d"
        ]
    },
    "timezone": "browser",
    "title": "Cluster",
    "uid": "Ss3q6hSZk3",
    "version": 2,
    "weekStart": ""
}
